meiro_mcp/__init__.py
meiro_mcp/__main__.py
meiro_mcp/auth.py
meiro_mcp/mcp_server.py
meiro_mcp/tools/__init__.py
meiro_mcp/tools/attribute.py
meiro_mcp/tools/customer.py
meiro_mcp/tools/event.py
meiro_mcp/tools/funnel.py
meiro_mcp/tools/segment.py
meiro_mcp-0.3.0.dist-info/METADATA
meiro_mcp-0.3.0.dist-info/WHEEL
meiro_mcp-0.3.0.dist-info/entry_points.txt
meiro_mcp-0.3.0.dist-info/top_level.txt
meiro_mcp-0.3.0.dist-info/RECORD
